dockerhub_cli/__init__.py
dockerhub_cli-0.1.0.dist-info/METADATA
dockerhub_cli-0.1.0.dist-info/WHEEL
dockerhub_cli-0.1.0.dist-info/entry_points.txt
dockerhub_cli-0.1.0.dist-info/RECORD
