Metadata-Version: 2.1
Name: dockerhub-cli
Version: 0.1.0
Summary: 
Author: None
Requires-Python: >=3.10,<4.0
Classifier: Programming Language :: Python :: 3
Classifier: Programming Language :: Python :: 3.10
Classifier: Programming Language :: Python :: 3.11
Requires-Dist: requests (>=2.28.2,<3.0.0)
Requires-Dist: rich (>=13.3.4,<14.0.0)
Requires-Dist: tabulate (>=0.9.0,<0.10.0)
